github_domain_scraper/__init__.py
github_domain_scraper/__main__.py
github_domain_scraper/constants.py
github_domain_scraper/driver.py
github_domain_scraper/exceptions.py
github_domain_scraper/extractor.py
github_domain_scraper/logger.py
github_domain_scraper/backends/__init__.py
github_domain_scraper/backends/base.py
github_domain_scraper/backends/list_repositories.py
github_domain_scraper/backends/stargazer_profile.py
github_domain_scraper/backends/user_profile.py
github_domain_scraper/interfaces/__init__.py
github_domain_scraper/interfaces/stargazer_profile.py
github_domain_scraper/interfaces/user_profile.py
github_domain_scraper-3.2.0.dist-info/licenses/LICENSE
github_domain_scraper-3.2.0.dist-info/METADATA
github_domain_scraper-3.2.0.dist-info/WHEEL
github_domain_scraper-3.2.0.dist-info/entry_points.txt
github_domain_scraper-3.2.0.dist-info/top_level.txt
github_domain_scraper-3.2.0.dist-info/RECORD
