Metadata-Version: 2.4
Name: github-domain-scraper
Version: 3.2.0
Summary: This Python package is designed for web crawling through input links that belong to GitHub domains. It offers a wide range of functionalities beyond simple crawling, including the ability to list repositories associated with the provided link, download GitHub repositories, and extract the contents of GitHub repositories.
Author-email: Parth971 <desaiparth971@gmail.com>
License: MIT License
Project-URL: repository, https://github.com/Parth971/github-domain-scraper
Keywords: github,crawler,extractor,scraper,github-domain
Classifier: License :: OSI Approved :: MIT License
Classifier: Programming Language :: Python
Classifier: Programming Language :: Python :: 3
Requires-Python: >=3.8
License-File: LICENSE
Requires-Dist: selenium>=4.5.0
Requires-Dist: webdriver-manager>=4.0.0
Requires-Dist: undetected-chromedriver>=3.1.5
Requires-Dist: beautifulsoup4>=4.13.0
Requires-Dist: lxml>=5.0.0
Requires-Dist: pandas>=2.3.0
Provides-Extra: build
Requires-Dist: build; extra == "build"
Requires-Dist: twine; extra == "build"
Provides-Extra: dev
Requires-Dist: black; extra == "dev"
Requires-Dist: bumpver; extra == "dev"
Requires-Dist: isort; extra == "dev"
Requires-Dist: mypy; extra == "dev"
Requires-Dist: pytest; extra == "dev"
Dynamic: license-file
